{"features":{"tenure":"Freehold","sqm":"90 sqm","propertyType":"Semi-detached house ","bedrooms":"3 beds","bathrooms":"2 baths","receptions":"1 reception"},"uprn":"100020937766","address":{"address":"14 Badgers Croft, London, SE9 3DB","lat":51.43066,"lng":0.05947},"nearbyPOIs":[{"category":"Academy","distanceMiles":0.24720758117593256,"lat":51.43411764,"lng":0.05685689,"name":"Greenacres Primary School and Language Impairment Unit","gender":"Mixed"},{"category":"State school","distanceMiles":0.25152619370377,"lat":51.42780477,"lng":0.06247123,"name":"Montbelle Primary School","gender":"Mixed"},{"distanceMiles":0.7,"lat":51.437705,"lng":0.070383,"name":"New Eltham"},{"distanceMiles":0.7,"lat":51.439856,"lng":0.050334,"name":"Mottingham"}],"soldDate":"2025-03-02T00:00:00.000Z","priceStr":"£450,000","price":450000,"crime":{"antiSocial":49,"burglary":7,"criminalDamage":30,"drugs":7,"theft":45,"weaponPossession":2,"publicOrder":15,"robbery":3,"vehicle":22,"violence":79,"other":3}}