{"features":{"tenure":"Freehold","sqm":"174 sqm","propertyType":"Semi-detached house ","bedrooms":"4 beds","bathrooms":"3 baths","receptions":"1 reception"},"uprn":"100023052366","address":{"address":"3 Glen Rise, Woodford Green, IG8 0AW","lat":51.60635,"lng":0.03077},"nearbyPOIs":[{"distanceMiles":0.1,"lat":51.607033,"lng":0.034037,"name":"Woodford"},{"category":"Independent school","distanceMiles":0.2975742204463433,"lat":51.60867251,"lng":0.02503479,"name":"Woodford Green Preparatory School","gender":"Mixed"},{"category":"State school","distanceMiles":0.38479586187291215,"lat":51.60096813,"lng":0.0332262,"name":"Woodbridge High School","gender":"Mixed"},{"distanceMiles":0.9,"lat":51.617115,"lng":0.043864,"name":"Roding Valley"}],"soldDate":"2025-04-01T23:00:00.000Z","priceStr":"£1,000,000","price":1000000,"crime":{"antiSocial":46,"burglary":11,"criminalDamage":8,"drugs":13,"theft":46,"weaponPossession":2,"publicOrder":12,"robbery":22,"vehicle":35,"violence":71,"other":2}}