{"features":{"tenure":"Freehold","sqm":"194 sqm","epcRating":"EPC rating: C","propertyType":"Semi-detached house ","bedrooms":"5 beds","bathrooms":"2 baths","receptions":"2 receptions"},"uprn":"100020422455","address":{"address":"25 Downs Avenue, Chislehurst, BR7 6HG","lat":51.42156,"lng":0.04972},"nearbyPOIs":[{"category":"Academy","distanceMiles":0.2697595152683329,"lat":51.42417865,"lng":0.04461523,"name":"Elmstead Wood Primary School","gender":"Mixed"},{"category":"Independent school","distanceMiles":0.27979146335401256,"lat":51.41839204,"lng":0.0494912,"name":"Babington House School","gender":"Mixed"},{"distanceMiles":0.5,"lat":51.417119,"lng":0.044283,"name":"Elmstead Woods"},{"distanceMiles":1.2,"lat":51.439856,"lng":0.050334,"name":"Mottingham"}],"soldDate":"2025-03-02T00:00:00.000Z","priceStr":"£770,000","price":770000,"crime":{"antiSocial":36,"burglary":9,"criminalDamage":23,"drugs":5,"theft":38,"weaponPossession":2,"publicOrder":10,"robbery":3,"vehicle":21,"violence":65,"other":1}}