{"features":{"tenure":"Freehold","sqm":"55 sqm","epcRating":"EPC rating: D","bedrooms":"2 beds","bathrooms":"1 bath"},"uprn":"100022629300","address":{"address":"198 Coteford Street, London, SW17 8NL","lat":51.42689,"lng":-0.15753},"nearbyPOIs":[{"category":"Academy","distanceMiles":0.08761661230911476,"lat":51.42763138,"lng":-0.15993289,"name":"Franciscan Primary School","gender":"Mixed"},{"category":"Academy","distanceMiles":0.18440764923471922,"lat":51.42682961,"lng":-0.16213725,"name":"Tooting Primary School","gender":"Mixed"},{"distanceMiles":0.4,"lat":51.427435,"lng":-0.167977,"name":"Tooting Broadway"},{"distanceMiles":0.5,"lat":51.41989,"lng":-0.16099,"name":"Tooting"}],"soldDate":"2025-03-02T00:00:00.000Z","priceStr":"£542,000","price":542000,"crime":{"antiSocial":151,"theft":165,"burglary":20,"criminalDamage":24,"drugs":17,"weaponPossession":3,"publicOrder":36,"robbery":21,"vehicle":55,"violence":174,"other":7}}