{"features":{"tenure":"Freehold","sqm":"114 sqm","epcRating":"EPC rating: D","propertyType":"Semi-detached house ","bedrooms":"3 beds","bathrooms":"1 bath","receptions":"2 receptions"},"uprn":"100020954922","address":{"address":"83 Crookston Road, London, SE9 1YQ","lat":51.46351,"lng":0.06109},"nearbyPOIs":[{"category":"Academy","distanceMiles":0.08510617660363476,"lat":51.46230638,"lng":0.06219863,"name":"Deansfield Primary School","gender":"Mixed"},{"category":"State school","distanceMiles":0.44411272575658156,"lat":51.46990198,"lng":0.06085654,"name":"Christ Church Church of England Primary School, Shooters Hill","gender":"Mixed"},{"distanceMiles":0.7,"lat":51.455649,"lng":0.052338,"name":"Eltham"},{"distanceMiles":0.8,"lat":51.459144,"lng":0.078551,"name":"Falconwood"}],"soldDate":"2025-03-02T00:00:00.000Z","priceStr":"£680,000","price":680000,"crime":{"antiSocial":51,"theft":46,"burglary":15,"criminalDamage":16,"drugs":13,"weaponPossession":1,"publicOrder":11,"robbery":9,"vehicle":16,"violence":81,"other":10}}