{"features":{"sqm":"198 sqm","epcRating":"EPC rating: C","propertyType":"Flat/Maisonette "},"uprn":"100021877558","address":{"address":"160–162 Old South Lambeth Road, London, SW8 1XX","lat":51.48016,"lng":-0.12374},"nearbyPOIs":[{"category":"State school","distanceMiles":0.05980773808458601,"lat":51.47974127,"lng":-0.12229389,"name":"St Stephen's Church of England Primary School","gender":"Mixed"},{"category":"State school","distanceMiles":0.12082035854360533,"lat":51.48129364,"lng":-0.12545627,"name":"Wyvil Primary School and Resource Bases for Speech, Language and Communication Needs, and Autism","gender":"Mixed"},{"distanceMiles":0.2,"lat":51.479934,"lng":-0.128558,"name":"Nine Elms"},{"distanceMiles":0.4,"lat":51.485733,"lng":-0.123749,"name":"Vauxhall"}],"soldDate":"2025-03-02T00:00:00.000Z","priceStr":"£1,700,000","price":1700000,"crime":{"antiSocial":252,"theft":298,"burglary":48,"criminalDamage":64,"drugs":43,"weaponPossession":3,"publicOrder":56,"robbery":55,"vehicle":53,"violence":264,"other":11}}