{"features":{"tenure":"Leasehold","sqm":"76 sqm","epcRating":"EPC rating: D","propertyType":"Purpose built flat ","bedrooms":"2 beds","bathrooms":"1 bath","receptions":"1 reception"},"uprn":"100022550172","address":{"address":"7 Hale Close, London, E4 6SA","lat":51.6229299,"lng":-0.00523},"nearbyPOIs":[{"category":"Academy","distanceMiles":0.3995263918031197,"lat":51.62052976,"lng":0.0037774,"name":"Longshaw Primary Academy","gender":"Mixed"},{"category":"State school","distanceMiles":0.4319878822054203,"lat":51.62512352,"lng":-0.01413747,"name":"Parkside Primary School","gender":"Mixed"},{"distanceMiles":0.9,"lat":51.633094,"lng":0.009906,"name":"Chingford"},{"distanceMiles":1,"lat":51.60889,"lng":0.000171,"name":"Highams Park"}],"soldDate":"2025-03-02T00:00:00.000Z","priceStr":"£375,000","price":375000,"crime":{"antiSocial":58,"burglary":17,"criminalDamage":12,"drugs":10,"theft":34,"publicOrder":9,"robbery":3,"vehicle":34,"violence":72}}