{"features":{"tenure":"Leasehold","sqm":"55 sqm","propertyType":"Flat/Maisonette ","bedrooms":"1 bed","bathrooms":"1 bath","receptions":"1 reception"},"uprn":"10033627511","address":{"address":"Flat 10, Waterfront Apartments, 82 Amberley Road, City of Westminster, London, W9 2JY","lat":51.52285065,"lng":-0.19167599117806178},"nearbyPOIs":[{"category":"Academy","distanceMiles":0.01833247654323749,"lat":51.52303314,"lng":-0.19160955,"name":"Ark Atwood Primary Academy","gender":"Mixed"},{"category":"State school","distanceMiles":0.0880298041438002,"lat":51.52255556,"lng":-0.18979776,"name":"St Mary Magdalene CofE Primary School","gender":"Mixed"},{"distanceMiles":0.3,"lat":51.519017,"lng":-0.18823,"name":"Royal Oak"},{"distanceMiles":0.3,"lat":51.523273,"lng":-0.183678,"name":"Warwick Avenue"}],"soldDate":"2025-03-02T00:00:00.000Z","priceStr":"£535,000","price":535000,"crime":{"antiSocial":400,"theft":467,"burglary":119,"criminalDamage":86,"drugs":55,"weaponPossession":12,"publicOrder":81,"robbery":57,"vehicle":112,"violence":351,"other":16}}