{"features":{"tenure":"Leasehold","sqm":"47 sqm","epcRating":"EPC rating: C","propertyType":"Purpose built flat ","bedrooms":"1 bed","bathrooms":"1 bath","receptions":"1 reception"},"uprn":"12097904","address":{"address":"52 Beardsley Way, London, W3 7YQ","lat":51.50476,"lng":-0.26283},"nearbyPOIs":[{"category":"Academy","distanceMiles":0.1542711557317764,"lat":51.50483692,"lng":-0.26639511,"name":"Ark Priory Primary Academy","gender":"Mixed"},{"category":"Academy","distanceMiles":0.1658341151487811,"lat":51.50715658,"lng":-0.26271891,"name":"Ark Byron Primary Academy","gender":"Mixed"},{"distanceMiles":0.3,"lat":51.508776,"lng":-0.263617,"name":"Acton Central"},{"distanceMiles":0.5,"lat":51.4997,"lng":-0.270157,"name":"South Acton"}],"soldDate":"2025-03-02T00:00:00.000Z","priceStr":"£300,000","price":300000,"crime":{"antiSocial":142,"theft":125,"burglary":26,"criminalDamage":39,"drugs":13,"weaponPossession":4,"publicOrder":28,"robbery":19,"vehicle":105,"violence":168,"other":9}}