{"features":{"tenure":"Freehold","sqm":"108 sqm","epcRating":"EPC rating: C","propertyType":"Mid terrace house ","bedrooms":"2 beds","bathrooms":"2 baths","receptions":"1 reception"},"uprn":"200003969991","address":{"address":"5 Bailey Mews, London, W4 3PZ","lat":51.48547,"lng":-0.2761},"nearbyPOIs":[{"category":"State school","distanceMiles":0.21215932431475185,"lat":51.48457526,"lng":-0.27118225,"name":"Grove Park Primary School","gender":"Mixed"},{"category":"State school","distanceMiles":0.23662328097038296,"lat":51.48746179,"lng":-0.28034922,"name":"Strand-on-the-Green Junior School","gender":"Mixed"},{"distanceMiles":0.4,"lat":51.491869,"lng":-0.275783,"name":"Gunnersbury"},{"distanceMiles":0.4,"lat":51.491793,"lng":-0.275175,"name":"Gunnersbury"}],"soldDate":"2025-04-01T23:00:00.000Z","priceStr":"£900,000","price":900000,"crime":{"antiSocial":57,"theft":75,"burglary":19,"criminalDamage":19,"drugs":14,"publicOrder":22,"robbery":8,"vehicle":72,"violence":85,"other":2}}