{"features":{"tenure":"Freehold","propertyType":"Semi-detached house "},"uprn":"5185008","address":{"address":"Sunnyfield House, 48B Minster Road, London, NW2 3RD","lat":51.5074456,"lng":-0.1277653},"nearbyPOIs":[{"category":"Independent school","distanceMiles":0.1513390811224946,"lat":51.55152893,"lng":-0.20731228,"name":"The Mulberry House School","gender":"Mixed"},{"category":"State school","distanceMiles":0.20657159235067205,"lat":51.55587592,"lng":-0.20695396,"name":"Hampstead School","gender":"Mixed"},{"distanceMiles":0.4,"lat":51.54688,"lng":-0.204633,"name":"Kilburn"},{"distanceMiles":0.5,"lat":51.55872,"lng":-0.21223,"name":"Cricklewood"}],"soldDate":"2025-03-02T00:00:00.000Z","priceStr":"£890,000","price":890000,"crime":{"antiSocial":482,"theft":4203,"burglary":91,"criminalDamage":83,"drugs":89,"weaponPossession":7,"publicOrder":130,"robbery":229,"vehicle":178,"violence":497,"other":19}}