{"uprn": "100020271283", "sold_date": "2025-03-02T00:00:00.000Z", "price": 320000, "price_str": "\u00a3320,000", "tenure": "leasehold", "sqm": 68, "epc_rating": "c", "property_type": "flat", "bedrooms": 1, "bathrooms": 1, "receptions": 1, "address": "1 jubilee flats, lulworth road, welling, da16 3lg", "city": "welling", "postcode": "da16 3lg", "lat": 50.3290749, "lng": 7.3135216, "num_pois": 4, "num_schools": 1, "avg_distance_all": 0.42251428772375577, "min_distance_school": 0.29855915850184916, "closest_school_gender": "Mixed", "closest_school_name": "St Stephen's Catholic Primary School", "closest_poi_name": "Welling", "street": "1 jubilee flats lulworth road"}