{"uprn": "100021576883", "sold_date": "2025-03-02T00:00:00.000Z", "price": 495000, "price_str": "\u00a3495,000", "tenure": "freehold", "sqm": 87, "epc_rating": null, "property_type": "mid terrace house", "bedrooms": 2, "bathrooms": 1, "receptions": 1, "address": "2 harlequin close, isleworth, tw7 7la", "city": "isleworth", "postcode": "tw7 7la", "lat": 51.45838, "lng": -0.34392, "crime_antiSocial": 47, "crime_theft": 72, "crime_burglary": 11, "crime_criminalDamage": 18, "crime_drugs": 8, "crime_publicOrder": 10, "crime_robbery": 5, "crime_vehicle": 42, "crime_violence": 92, "crime_other": 5, "num_pois": 4, "num_schools": 2, "avg_distance_all": 0.6061969827581921, "min_distance_school": 0.34207729090238004, "closest_school_gender": "Mixed", "closest_school_name": "Chase Bridge Primary School", "closest_poi_name": "Chase Bridge Primary School", "street": "2 harlequin close"}