{"uprn": "100020437886", "sold_date": "2025-04-01T23:00:00.000Z", "price": 272000, "price_str": "\u00a3272,000", "tenure": "leasehold", "sqm": 65, "epc_rating": "d", "property_type": "flat", "bedrooms": 2, "bathrooms": null, "receptions": 0, "address": "flat 3, readman court, 42 jasmine grove, london, se20 8jz", "city": "london", "postcode": "se20 8jz", "lat": 50.4438552, "lng": -3.587063925906344, "crime_antiSocial": 31, "crime_burglary": 5, "crime_criminalDamage": 12, "crime_drugs": 8, "crime_theft": 39, "crime_publicOrder": 8, "crime_robbery": 3, "crime_vehicle": 3, "crime_violence": 76, "crime_other": 4, "num_pois": 4, "num_schools": 0, "avg_distance_all": 0.26718527656144364, "min_distance_school": null, "closest_school_gender": null, "closest_school_name": null, "closest_poi_name": "St Anthony's Catholic Primary School", "street": "flat 3 readman court 42 jasmine grove"}