{"uprn": "10002264144", "sold_date": "2025-03-02T00:00:00.000Z", "price": 375000, "price_str": "\u00a3375,000", "tenure": "leasehold", "sqm": 62, "epc_rating": null, "property_type": "flat", "bedrooms": 2, "bathrooms": 1, "receptions": 1, "address": "41 chertsey court, clifford avenue, london, sw14 7rd", "city": "london", "postcode": "sw14 7rd", "lat": 51.5074456, "lng": -0.1277653, "crime_antiSocial": 482, "crime_theft": 4203, "crime_burglary": 91, "crime_criminalDamage": 83, "crime_drugs": 89, "crime_weaponPossession": 7, "crime_publicOrder": 130, "crime_robbery": 229, "crime_vehicle": 178, "crime_violence": 497, "crime_other": 19, "num_pois": 4, "num_schools": 1, "avg_distance_all": 0.4019197189087603, "min_distance_school": 0.37079549265414974, "closest_school_gender": "Mixed", "closest_school_name": "Kew Riverside Primary School", "closest_poi_name": "Mortlake", "street": "41 chertsey court clifford avenue"}