{"uprn": "100021802358", "sold_date": "2025-03-02T00:00:00.000Z", "price": 960000, "price_str": "\u00a3960,000", "tenure": "freehold", "sqm": 150, "epc_rating": "d", "property_type": "semi-detached house", "bedrooms": 4, "bathrooms": 1, "receptions": 2, "address": "76 church road, worcester park, kt4 7rw", "city": "worcester park", "postcode": "kt4 7rw", "lat": 51.38348, "lng": -0.25794, "crime_antiSocial": 11, "crime_theft": 30, "crime_burglary": 3, "crime_criminalDamage": 6, "crime_drugs": 3, "crime_weaponPossession": 1, "crime_publicOrder": 8, "crime_robbery": 1, "crime_vehicle": 9, "crime_violence": 41, "crime_other": 3, "num_pois": 4, "num_schools": 2, "avg_distance_all": 0.27120499046971935, "min_distance_school": 0.08699060712315079, "closest_school_gender": "Mixed", "closest_school_name": "Malden Parochial CofE Primary School", "closest_poi_name": "Malden Parochial CofE Primary School", "street": "76 church road"}