{"uprn": "100021403587", "sold_date": "2025-03-02T00:00:00.000Z", "price": 560000, "price_str": "\u00a3560,000", "tenure": "freehold", "sqm": 105, "epc_rating": "d", "property_type": "detached house", "bedrooms": 3, "bathrooms": null, "receptions": 2, "address": "19 aldborough road, upminster, rm14 2rj", "city": "upminster", "postcode": "rm14 2rj", "lat": 51.55814, "lng": 0.23629, "crime_antiSocial": 23, "crime_burglary": 6, "crime_criminalDamage": 5, "crime_drugs": 5, "crime_theft": 53, "crime_publicOrder": 6, "crime_robbery": 6, "crime_vehicle": 23, "crime_violence": 33, "crime_other": 3, "num_pois": 4, "num_schools": 1, "avg_distance_all": 0.3728974326247216, "min_distance_school": 0.46831563799287157, "closest_school_gender": "Mixed", "closest_school_name": "Branfil Primary School", "closest_poi_name": "Upminster Bridge", "street": "19 aldborough road"}