{"uprn": "10008348564", "sold_date": "2025-03-02T00:00:00.000Z", "price": 790000, "price_str": "\u00a3790,000", "tenure": "leasehold", "sqm": 83, "epc_rating": "b", "property_type": "flat", "bedrooms": 2, "bathrooms": 2, "receptions": 1, "address": "flat 16, fisheries building, lamb lane, london, e8 3pl", "city": "london", "postcode": "e8 3pl", "lat": 40.138088, "lng": -88.462311, "num_pois": 4, "num_schools": 2, "avg_distance_all": 0.25235197358364647, "min_distance_school": 0.24928093734465717, "closest_school_gender": "Mixed", "closest_school_name": "London Fields Primary School", "closest_poi_name": "London Fields", "street": "flat 16 fisheries building lamb lane"}