{"uprn": "100020389320", "sold_date": "2025-03-02T00:00:00.000Z", "price": 500000, "price_str": "\u00a3500,000", "tenure": "freehold", "sqm": 112, "epc_rating": "c", "property_type": "mid terrace house", "bedrooms": 3, "bathrooms": 1, "receptions": 1, "address": "117 avondale road, bromley, br1 4hr", "city": "bromley", "postcode": "br1 4hr", "lat": 51.41795, "lng": 0.0051, "crime_antiSocial": 61, "crime_theft": 68, "crime_burglary": 12, "crime_criminalDamage": 28, "crime_drugs": 22, "crime_weaponPossession": 3, "crime_publicOrder": 19, "crime_robbery": 8, "crime_vehicle": 47, "crime_violence": 94, "crime_other": 6, "num_pois": 4, "num_schools": 0, "avg_distance_all": 0.5483558534735271, "min_distance_school": null, "closest_school_gender": null, "closest_school_name": null, "closest_poi_name": "Burnt Ash Primary School", "street": "117 avondale road"}