{"uprn": "100021197615", "sold_date": "2025-03-02T00:00:00.000Z", "price": 740000, "price_str": "\u00a3740,000", "tenure": "freehold", "sqm": 114, "epc_rating": "d", "property_type": "end terrace house", "bedrooms": 3, "bathrooms": 2, "receptions": 2, "address": "26 loobert road, london, n15 4lq", "city": "london", "postcode": "n15 4lq", "lat": 51.58874, "lng": -0.07599, "crime_antiSocial": 211, "crime_theft": 206, "crime_burglary": 37, "crime_criminalDamage": 52, "crime_drugs": 60, "crime_weaponPossession": 3, "crime_publicOrder": 38, "crime_robbery": 44, "crime_vehicle": 94, "crime_violence": 241, "crime_other": 16, "num_pois": 4, "num_schools": 1, "avg_distance_all": 0.3661584839568172, "min_distance_school": 0.3575683333271196, "closest_school_gender": "Mixed", "closest_school_name": "Bruce Grove Primary School", "closest_poi_name": "Holy Trinity CofE Primary School", "street": "26 loobert road"}