{"uprn": "10091040081", "sold_date": "2025-04-01T23:00:00.000Z", "price": 381500, "price_str": "\u00a3381,500", "tenure": "leasehold", "sqm": 73, "epc_rating": "b", "property_type": "flat", "bedrooms": 2, "bathrooms": null, "receptions": 1, "address": "flat 8, hitherwood court, 28 charcot road, london, nw9 5yw", "city": "london", "postcode": "nw9 5yw", "lat": 51.5954253, "lng": -0.2511126, "crime_antiSocial": 121, "crime_theft": 101, "crime_burglary": 42, "crime_criminalDamage": 45, "crime_drugs": 22, "crime_weaponPossession": 2, "crime_publicOrder": 30, "crime_robbery": 10, "crime_vehicle": 40, "crime_violence": 153, "crime_other": 10, "num_pois": 4, "num_schools": 1, "avg_distance_all": 0.38985179603148856, "min_distance_school": 0.3975048702079853, "closest_school_gender": "Girls", "closest_school_name": "Beis Yaakov Primary School", "closest_poi_name": "Colindale", "street": "flat 8 hitherwood court 28 charcot road"}