{"uprn": "200084914", "sold_date": "2025-03-02T00:00:00.000Z", "price": 700000, "price_str": "\u00a3700,000", "tenure": "freehold", "sqm": 127, "epc_rating": "d", "property_type": "detached house", "bedrooms": 3, "bathrooms": null, "receptions": 2, "address": "118 netherlands road, new barnet, barnet, en5 1bx", "city": "barnet", "postcode": "en5 1bx", "lat": 51.65309, "lng": -0.2002261, "crime_antiSocial": 52, "crime_burglary": 11, "crime_criminalDamage": 8, "crime_drugs": 15, "crime_theft": 52, "crime_weaponPossession": 1, "crime_publicOrder": 6, "crime_robbery": 2, "crime_vehicle": 18, "crime_violence": 64, "crime_other": 5, "num_pois": 4, "num_schools": 2, "avg_distance_all": 0.3505825526146057, "min_distance_school": 0.33033736333561997, "closest_school_gender": "Mixed", "closest_school_name": "St Mary's CofE Primary School, East Barnet", "closest_poi_name": "Oakleigh Park", "street": "118 netherlands road new barnet"}